biosimulators_ginsim/__init__.py
biosimulators_ginsim/__main__.py
biosimulators_ginsim/_version.py
biosimulators_ginsim/core.py
biosimulators_ginsim/data_model.py
biosimulators_ginsim/utils.py
biosimulators_ginsim-0.0.9.dist-info/LICENSE
biosimulators_ginsim-0.0.9.dist-info/METADATA
biosimulators_ginsim-0.0.9.dist-info/WHEEL
biosimulators_ginsim-0.0.9.dist-info/entry_points.txt
biosimulators_ginsim-0.0.9.dist-info/top_level.txt
biosimulators_ginsim-0.0.9.dist-info/RECORD
